README.md
setup.cfg
setup.py
pp_distributions/Binomialdistribution.py
pp_distributions/Gaussiandistribution.py
pp_distributions/Generaldistribution.py
pp_distributions/__init__.py
pp_distributions.egg-info/PKG-INFO
pp_distributions.egg-info/SOURCES.txt
pp_distributions.egg-info/dependency_links.txt
pp_distributions.egg-info/not-zip-safe
pp_distributions.egg-info/top_level.txt